Workbook

Sheet Datos_Importación
A1: No. | B1: Código | C1: Producto | D1: Categoría | E1: País Origen | F1: Cantidad | G1: Precio Unitario (USD) | H1: Importe Total (USD) | I1: Clasificación
A2: 1 | B2: MEX-001 | C2: Galletas integrales | D2: Alimentos | E2: México | F2: 120 | G2: 4.5 | H2: =F2*G2 -> 540 | I2: =IF(H2>1000,"Importe Alto","Importe Normal") -> Importe Normal
A3: 2 | B3: MEX-002 | C3: Café soluble | D3: Alimentos | E3: México | F3: 85 | G3: 8.75 | H3: =F3*G3 -> 743.75 | I3: =IF(H3>1000,"Importe Alto","Importe Normal") -> Importe Normal
A4: 3 | B4: MEX-003 | C4: Salsa de tomate | D4: Alimentos | E4: México | F4: 150 | G4: 3.2 | H4: =F4*G4 -> 480 | I4: =IF(H4>1000,"Importe Alto","Importe Normal") -> Importe Normal
A5: 4 | B5: MEX-004 | C5: Atún enlatado | D5: Alimentos | E5: México | F5: 200 | G5: 2.85 | H5: =F5*G5 -> 570 | I5: =IF(H5>1000,"Importe Alto","Importe Normal") -> Importe Normal
A6: 5 | B6: MEX-005 | C6: Aceite vegetal | D6: Alimentos | E6: México | F6: 180 | G6: 5.4 | H6: =F6*G6 -> 972 | I6: =IF(H6>1000,"Importe Alto","Importe Normal") -> Importe Normal
A7: 6 | B7: MEX-006 | C7: Cereal de maíz | D7: Alimentos | E7: México | F7: 95 | G7: 6.8 | H7: =F7*G7 -> 646 | I7: =IF(H7>1000,"Importe Alto","Importe Normal") -> Importe Normal
A8: 7 | B8: MEX-007 | C8: Leche en polvo | D8: Alimentos | E8: México | F8: 110 | G8: 9.5 | H8: =F8*G8 -> 1045 | I8: =IF(H8>1000,"Importe Alto","Importe Normal") -> Importe Alto
A9: 8 | B9: MEX-008 | C9: Frijoles enlatados | D9: Alimentos | E9: México | F9: 160 | G9: 3.75 | H9: =F9*G9 -> 600 | I9: =IF(H9>1000,"Importe Alto","Importe Normal") -> Importe Normal
A10: 9 | B10: MEX-009 | C10: Mayonesa | D10: Alimentos | E10: México | F10: 130 | G10: 4.25 | H10: =F10*G10 -> 552.5 | I10: =IF(H10>1000,"Importe Alto","Importe Normal") -> Importe Normal
A11: 10 | B11: MEX-010 | C11: Mermelada de fresa | D11: Alimentos | E11: México | F11: 90 | G11: 5.6 | H11: =F11*G11 -> 504 | I11: =IF(H11>1000,"Importe Alto","Importe Normal") -> Importe Normal
A12: 11 | B12: MEX-011 | C12: Chocolate en polvo | D12: Alimentos | E12: México | F12: 75 | G12: 7.25 | H12: =F12*G12 -> 543.75 | I12: =IF(H12>1000,"Importe Alto","Importe Normal") -> Importe Normal
A13: 12 | B13: MEX-012 | C13: Harina de trigo | D13: Alimentos | E13: México | F13: 220 | G13: 2.9 | H13: =F13*G13 -> 638 | I13: =IF(H13>1000,"Importe Alto","Importe Normal") -> Importe Normal
... A51: 50 | B51: MEX-050 | C51: Organizadores | D51: Hogar | E51: México | F51: 100 | G51: 10.5 | H51: =F51*G51 -> 1050 | I51: =IF(H51>1000,"Importe Alto","Importe Normal") -> Importe Alto

Sheet Resultados
A1: Resultados del Análisis — Importación México → Nicaragua
A2: NicaTrade International — Hoja Datos_Importación
A4: Indicador | B4: Valor
A5: Importe total de la operación (USD) | B5: =SUM(Datos_Importación!H2:H51) -> 40359
A6: Precio promedio de los productos (USD) | B6: =AVERAGE(Datos_Importación!G2:G51) -> 7.742
A7: Cantidad de productos registrados | B7: =COUNTA(Datos_Importación!A2:A51) -> 50
A8: Importe correspondiente a productos de México (USD) | B8: =SUMIF(Datos_Importación!E2:E51,"México",Datos_Importación!H2:H51) -> 36919.5
A9: Producto con mayor importe | B9: =INDEX(Datos_Importación!C2:C51,MATCH(MAX(Datos_Importación!H2:H51),Datos_Importación!H2:H51,0)) -> Mochilas
A10: Importe del producto con mayor importe (USD) | B10: =MAX(Datos_Importación!H2:H51) -> 1912.5
A12: Preguntas de Reflexión
A13: 1. ¿Cuál es el importe total de la operación?
A14: ="El importe total de la operación es de $"&TEXT(SUM(Datos_Importación!H2:H51),"#,##0.00")&" USD." -> El importe total de la operación es de $40,359.00 USD.
A16: 2. ¿Cuál es el producto con mayor importe?
A17: ="El producto con mayor importe es "&INDEX(Datos_Importación!C2:C51,MATCH(MAX(Datos_Importación!H2:H51),Datos_Importación!H2:H51,0))&", con un importe de $"&TEXT(MAX(Datos_Importación!H2:H51),"#,##0.00")&" USD." -> El producto con mayor importe es Mochilas, con un importe de $1,912.50 USD.
A19: 3. ¿Cuál es el precio promedio?
A20: ="El precio promedio de los productos es de $"&TEXT(AVERAGE(Datos_Importación!G2:G51),"#,##0.00")&" USD." -> El precio promedio de los productos es de $7.74 USD.
A22: 4. ¿Cuántos productos están registrados?
A23: ="Hay "&COUNTA(Datos_Importación!A2:A51)&" productos registrados en la operación." -> Hay 50 productos registrados en la operación.
A24: 5. ¿Por qué es importante analizar esta información antes de realizar una operación comercial?
A25: Analizar la información antes de realizar una operación comercial permite tomar decisiones basadas en datos reales: conocer el costo total de la importación, identificar qué productos representan mayor inversión, verificar el origen de los productos y anticipar riesgos financieros. Esto ayuda a NicaTrade International a planificar mejor sus recursos, negociar con proveedores, fijar precios de venta adecuados y evitar pérdidas por falta de control en la información.
